{
  "scrape_timestamp": "2026-02-15T14:19:01.019501+01:00",
  "scrape_metadata": {
    "total_facilities": 17,
    "hour": 14,
    "day_of_week": 6,
    "is_weekend": true,
    "pool_count": 9,
    "sauna_count": 7,
    "ice_rink_count": 1,
    "duration_ms": 4677.807569503784,
    "method": "api"
  },
  "ice_rinks": [
    {
      "pool_name": "Prinzregentenstadion - Eislaufbahn",
      "facility_type": "ice_rink",
      "occupancy_level": "67 % frei",
      "occupancy_percent": 67.0,
      "is_open": true,
      "timestamp": "2026-02-15T14:18:56.341919+01:00",
      "hour": 14,
      "day_of_week": 6,
      "day_name": "Sunday",
      "is_weekend": true,
      "raw_occupancy": "233/700 persons"
    }
  ],
  "pools": [
    {
      "pool_name": "Bad Giesing-Harlaching",
      "facility_type": "pool",
      "occupancy_level": "77 % frei",
      "occupancy_percent": 77.0,
      "is_open": true,
      "timestamp": "2026-02-15T14:18:56.341919+01:00",
      "hour": 14,
      "day_of_week": 6,
      "day_name": "Sunday",
      "is_weekend": true,
      "raw_occupancy": "70/311 persons"
    },
    {
      "pool_name": "Cosimawellenbad",
      "facility_type": "pool",
      "occupancy_level": "44 % frei",
      "occupancy_percent": 44.0,
      "is_open": true,
      "timestamp": "2026-02-15T14:18:56.341919+01:00",
      "hour": 14,
      "day_of_week": 6,
      "day_name": "Sunday",
      "is_weekend": true,
      "raw_occupancy": "298/530 persons"
    },
    {
      "pool_name": "Dante-Winter-Warmfreibad",
      "facility_type": "pool",
      "occupancy_level": "79 % frei",
      "occupancy_percent": 79.0,
      "is_open": true,
      "timestamp": "2026-02-15T14:18:56.341919+01:00",
      "hour": 14,
      "day_of_week": 6,
      "day_name": "Sunday",
      "is_weekend": true,
      "raw_occupancy": "107/500 persons"
    },
    {
      "pool_name": "Michaelibad",
      "facility_type": "pool",
      "occupancy_level": "29 % frei",
      "occupancy_percent": 29.0,
      "is_open": true,
      "timestamp": "2026-02-15T14:18:56.341919+01:00",
      "hour": 14,
      "day_of_week": 6,
      "day_name": "Sunday",
      "is_weekend": true,
      "raw_occupancy": "402/570 persons"
    },
    {
      "pool_name": "M端ller'sches Volksbad",
      "facility_type": "pool",
      "occupancy_level": "70 % frei",
      "occupancy_percent": 70.0,
      "is_open": true,
      "timestamp": "2026-02-15T14:18:56.341919+01:00",
      "hour": 14,
      "day_of_week": 6,
      "day_name": "Sunday",
      "is_weekend": true,
      "raw_occupancy": "53/177 persons"
    },
    {
      "pool_name": "Nordbad",
      "facility_type": "pool",
      "occupancy_level": "46 % frei",
      "occupancy_percent": 46.0,
      "is_open": true,
      "timestamp": "2026-02-15T14:18:56.341919+01:00",
      "hour": 14,
      "day_of_week": 6,
      "day_name": "Sunday",
      "is_weekend": true,
      "raw_occupancy": "232/432 persons"
    },
    {
      "pool_name": "Olympia-Schwimmhalle",
      "facility_type": "pool",
      "occupancy_level": "66 % frei",
      "occupancy_percent": 66.0,
      "is_open": true,
      "timestamp": "2026-02-15T14:18:56.341919+01:00",
      "hour": 14,
      "day_of_week": 6,
      "day_name": "Sunday",
      "is_weekend": true,
      "raw_occupancy": "326/959 persons"
    },
    {
      "pool_name": "S端dbad",
      "facility_type": "pool",
      "occupancy_level": "51 % frei",
      "occupancy_percent": 51.0,
      "is_open": true,
      "timestamp": "2026-02-15T14:18:56.341919+01:00",
      "hour": 14,
      "day_of_week": 6,
      "day_name": "Sunday",
      "is_weekend": true,
      "raw_occupancy": "154/314 persons"
    },
    {
      "pool_name": "Westbad",
      "facility_type": "pool",
      "occupancy_level": "21 % frei",
      "occupancy_percent": 21.0,
      "is_open": true,
      "timestamp": "2026-02-15T14:18:56.341919+01:00",
      "hour": 14,
      "day_of_week": 6,
      "day_name": "Sunday",
      "is_weekend": true,
      "raw_occupancy": "689/872 persons"
    }
  ],
  "saunas": [
    {
      "pool_name": "Cosimawellenbad",
      "facility_type": "sauna",
      "occupancy_level": "72 % frei",
      "occupancy_percent": 72.0,
      "is_open": true,
      "timestamp": "2026-02-15T14:18:56.341919+01:00",
      "hour": 14,
      "day_of_week": 6,
      "day_name": "Sunday",
      "is_weekend": true,
      "raw_occupancy": "47/170 persons"
    },
    {
      "pool_name": "Dantebad",
      "facility_type": "sauna",
      "occupancy_level": "49 % frei",
      "occupancy_percent": 49.0,
      "is_open": true,
      "timestamp": "2026-02-15T14:18:56.341919+01:00",
      "hour": 14,
      "day_of_week": 6,
      "day_name": "Sunday",
      "is_weekend": true,
      "raw_occupancy": "77/150 persons"
    },
    {
      "pool_name": "Michaelibad",
      "facility_type": "sauna",
      "occupancy_level": "73 % frei",
      "occupancy_percent": 73.0,
      "is_open": true,
      "timestamp": "2026-02-15T14:18:56.341919+01:00",
      "hour": 14,
      "day_of_week": 6,
      "day_name": "Sunday",
      "is_weekend": true,
      "raw_occupancy": "40/150 persons"
    },
    {
      "pool_name": "M端ller'sches Volksbad",
      "facility_type": "sauna",
      "occupancy_level": "41 % frei",
      "occupancy_percent": 41.0,
      "is_open": true,
      "timestamp": "2026-02-15T14:18:56.341919+01:00",
      "hour": 14,
      "day_of_week": 6,
      "day_name": "Sunday",
      "is_weekend": true,
      "raw_occupancy": "41/70 persons"
    },
    {
      "pool_name": "Nordbad",
      "facility_type": "sauna",
      "occupancy_level": "66 % frei",
      "occupancy_percent": 66.0,
      "is_open": true,
      "timestamp": "2026-02-15T14:18:56.341919+01:00",
      "hour": 14,
      "day_of_week": 6,
      "day_name": "Sunday",
      "is_weekend": true,
      "raw_occupancy": "50/146 persons"
    },
    {
      "pool_name": "S端dbad",
      "facility_type": "sauna",
      "occupancy_level": "47 % frei",
      "occupancy_percent": 47.0,
      "is_open": true,
      "timestamp": "2026-02-15T14:18:56.341919+01:00",
      "hour": 14,
      "day_of_week": 6,
      "day_name": "Sunday",
      "is_weekend": true,
      "raw_occupancy": "53/100 persons"
    },
    {
      "pool_name": "Westbad",
      "facility_type": "sauna",
      "occupancy_level": "65 % frei",
      "occupancy_percent": 65.0,
      "is_open": true,
      "timestamp": "2026-02-15T14:18:56.341919+01:00",
      "hour": 14,
      "day_of_week": 6,
      "day_name": "Sunday",
      "is_weekend": true,
      "raw_occupancy": "21/60 persons"
    }
  ],
  "summary": {
    "avg_pool_occupancy": 53.666666666666664,
    "busiest_pool": "Dante-Winter-Warmfreibad",
    "quietest_pool": "Westbad"
  }
}