{
  "scrape_timestamp": "2026-01-17T13:25:04.064928+01:00",
  "scrape_metadata": {
    "total_facilities": 13,
    "pools_count": 7,
    "saunas_count": 6,
    "unknown_count": 0,
    "scrape_duration_ms": 4813.309669494629,
    "hour": 13,
    "day_of_week": 5,
    "is_weekend": true,
    "duration_ms": 4813.309669494629,
    "method": "api"
  },
  "pools": [
    {
      "pool_name": "Bad Giesing-Harlaching",
      "facility_type": "pool",
      "occupancy_level": "84 % frei",
      "occupancy_percent": 84.0,
      "is_open": true,
      "timestamp": "2026-01-17T13:24:59.251873+01:00",
      "hour": 13,
      "day_of_week": 5,
      "day_name": "Saturday",
      "is_weekend": true,
      "raw_occupancy": "51/311 persons"
    },
    {
      "pool_name": "Cosimawellenbad",
      "facility_type": "pool",
      "occupancy_level": "71 % frei",
      "occupancy_percent": 71.0,
      "is_open": true,
      "timestamp": "2026-01-17T13:24:59.251873+01:00",
      "hour": 13,
      "day_of_week": 5,
      "day_name": "Saturday",
      "is_weekend": true,
      "raw_occupancy": "153/530 persons"
    },
    {
      "pool_name": "Michaelibad",
      "facility_type": "pool",
      "occupancy_level": "44 % frei",
      "occupancy_percent": 44.0,
      "is_open": true,
      "timestamp": "2026-01-17T13:24:59.251873+01:00",
      "hour": 13,
      "day_of_week": 5,
      "day_name": "Saturday",
      "is_weekend": true,
      "raw_occupancy": "318/570 persons"
    },
    {
      "pool_name": "Nordbad",
      "facility_type": "pool",
      "occupancy_level": "77 % frei",
      "occupancy_percent": 77.0,
      "is_open": true,
      "timestamp": "2026-01-17T13:24:59.251873+01:00",
      "hour": 13,
      "day_of_week": 5,
      "day_name": "Saturday",
      "is_weekend": true,
      "raw_occupancy": "41/177 persons"
    },
    {
      "pool_name": "Südbad",
      "facility_type": "pool",
      "occupancy_level": "70 % frei",
      "occupancy_percent": 70.0,
      "is_open": true,
      "timestamp": "2026-01-17T13:24:59.251873+01:00",
      "hour": 13,
      "day_of_week": 5,
      "day_name": "Saturday",
      "is_weekend": true,
      "raw_occupancy": "131/432 persons"
    },
    {
      "pool_name": "Westbad",
      "facility_type": "pool",
      "occupancy_level": "66 % frei",
      "occupancy_percent": 66.0,
      "is_open": true,
      "timestamp": "2026-01-17T13:24:59.251873+01:00",
      "hour": 13,
      "day_of_week": 5,
      "day_name": "Saturday",
      "is_weekend": true,
      "raw_occupancy": "106/314 persons"
    },
    {
      "pool_name": "Müller'sches Volksbad",
      "facility_type": "pool",
      "occupancy_level": "62 % frei",
      "occupancy_percent": 62.0,
      "is_open": true,
      "timestamp": "2026-01-17T13:24:59.251873+01:00",
      "hour": 13,
      "day_of_week": 5,
      "day_name": "Saturday",
      "is_weekend": true,
      "raw_occupancy": "328/872 persons"
    }
  ],
  "saunas": [
    {
      "pool_name": "Cosimawellenbad Sauna",
      "facility_type": "sauna",
      "occupancy_level": "88 % frei",
      "occupancy_percent": 88.0,
      "is_open": true,
      "timestamp": "2026-01-17T13:24:59.251873+01:00",
      "hour": 13,
      "day_of_week": 5,
      "day_name": "Saturday",
      "is_weekend": true,
      "raw_occupancy": "20/170 persons"
    },
    {
      "pool_name": "Dantebad Sauna",
      "facility_type": "sauna",
      "occupancy_level": "61 % frei",
      "occupancy_percent": 61.0,
      "is_open": true,
      "timestamp": "2026-01-17T13:24:59.251873+01:00",
      "hour": 13,
      "day_of_week": 5,
      "day_name": "Saturday",
      "is_weekend": true,
      "raw_occupancy": "59/150 persons"
    },
    {
      "pool_name": "Michaelibad Sauna",
      "facility_type": "sauna",
      "occupancy_level": "89 % frei",
      "occupancy_percent": 89.0,
      "is_open": true,
      "timestamp": "2026-01-17T13:24:59.251873+01:00",
      "hour": 13,
      "day_of_week": 5,
      "day_name": "Saturday",
      "is_weekend": true,
      "raw_occupancy": "17/150 persons"
    },
    {
      "pool_name": "Nordbad Sauna",
      "facility_type": "sauna",
      "occupancy_level": "80 % frei",
      "occupancy_percent": 80.0,
      "is_open": true,
      "timestamp": "2026-01-17T13:24:59.251873+01:00",
      "hour": 13,
      "day_of_week": 5,
      "day_name": "Saturday",
      "is_weekend": true,
      "raw_occupancy": "29/146 persons"
    },
    {
      "pool_name": "Südbad Sauna",
      "facility_type": "sauna",
      "occupancy_level": "76 % frei",
      "occupancy_percent": 76.0,
      "is_open": true,
      "timestamp": "2026-01-17T13:24:59.251873+01:00",
      "hour": 13,
      "day_of_week": 5,
      "day_name": "Saturday",
      "is_weekend": true,
      "raw_occupancy": "24/100 persons"
    },
    {
      "pool_name": "Westbad Sauna",
      "facility_type": "sauna",
      "occupancy_level": "87 % frei",
      "occupancy_percent": 87.0,
      "is_open": true,
      "timestamp": "2026-01-17T13:24:59.251873+01:00",
      "hour": 13,
      "day_of_week": 5,
      "day_name": "Saturday",
      "is_weekend": true,
      "raw_occupancy": "8/60 persons"
    }
  ],
  "unknown_facilities": [],
  "summary": {
    "avg_pool_occupancy": 67.71428571428571,
    "avg_sauna_occupancy": 80.16666666666667,
    "busiest_pool": "Bad Giesing-Harlaching",
    "quietest_pool": "Michaelibad"
  }
}