{
  "scrape_timestamp": "2026-02-15T17:24:21.816802+01:00",
  "scrape_metadata": {
    "total_facilities": 17,
    "hour": 17,
    "day_of_week": 6,
    "is_weekend": true,
    "pool_count": 9,
    "sauna_count": 7,
    "ice_rink_count": 1,
    "duration_ms": 5552.490472793579,
    "method": "api"
  },
  "ice_rinks": [
    {
      "pool_name": "Prinzregentenstadion - Eislaufbahn",
      "facility_type": "ice_rink",
      "occupancy_level": "78 % frei",
      "occupancy_percent": 78.0,
      "is_open": true,
      "timestamp": "2026-02-15T17:24:16.264513+01:00",
      "hour": 17,
      "day_of_week": 6,
      "day_name": "Sunday",
      "is_weekend": true,
      "raw_occupancy": "153/700 persons"
    }
  ],
  "pools": [
    {
      "pool_name": "Bad Giesing-Harlaching",
      "facility_type": "pool",
      "occupancy_level": "80 % frei",
      "occupancy_percent": 80.0,
      "is_open": true,
      "timestamp": "2026-02-15T17:24:16.264513+01:00",
      "hour": 17,
      "day_of_week": 6,
      "day_name": "Sunday",
      "is_weekend": true,
      "raw_occupancy": "61/311 persons"
    },
    {
      "pool_name": "Cosimawellenbad",
      "facility_type": "pool",
      "occupancy_level": "43 % frei",
      "occupancy_percent": 43.0,
      "is_open": true,
      "timestamp": "2026-02-15T17:24:16.264513+01:00",
      "hour": 17,
      "day_of_week": 6,
      "day_name": "Sunday",
      "is_weekend": true,
      "raw_occupancy": "303/530 persons"
    },
    {
      "pool_name": "Dante-Winter-Warmfreibad",
      "facility_type": "pool",
      "occupancy_level": "75 % frei",
      "occupancy_percent": 75.0,
      "is_open": true,
      "timestamp": "2026-02-15T17:24:16.264513+01:00",
      "hour": 17,
      "day_of_week": 6,
      "day_name": "Sunday",
      "is_weekend": true,
      "raw_occupancy": "127/500 persons"
    },
    {
      "pool_name": "Michaelibad",
      "facility_type": "pool",
      "occupancy_level": "15 % frei",
      "occupancy_percent": 15.0,
      "is_open": true,
      "timestamp": "2026-02-15T17:24:16.264513+01:00",
      "hour": 17,
      "day_of_week": 6,
      "day_name": "Sunday",
      "is_weekend": true,
      "raw_occupancy": "487/570 persons"
    },
    {
      "pool_name": "M端ller'sches Volksbad",
      "facility_type": "pool",
      "occupancy_level": "59 % frei",
      "occupancy_percent": 59.0,
      "is_open": true,
      "timestamp": "2026-02-15T17:24:16.264513+01:00",
      "hour": 17,
      "day_of_week": 6,
      "day_name": "Sunday",
      "is_weekend": true,
      "raw_occupancy": "73/177 persons"
    },
    {
      "pool_name": "Nordbad",
      "facility_type": "pool",
      "occupancy_level": "43 % frei",
      "occupancy_percent": 43.0,
      "is_open": true,
      "timestamp": "2026-02-15T17:24:16.264513+01:00",
      "hour": 17,
      "day_of_week": 6,
      "day_name": "Sunday",
      "is_weekend": true,
      "raw_occupancy": "247/432 persons"
    },
    {
      "pool_name": "Olympia-Schwimmhalle",
      "facility_type": "pool",
      "occupancy_level": "60 % frei",
      "occupancy_percent": 60.0,
      "is_open": true,
      "timestamp": "2026-02-15T17:24:16.264513+01:00",
      "hour": 17,
      "day_of_week": 6,
      "day_name": "Sunday",
      "is_weekend": true,
      "raw_occupancy": "383/959 persons"
    },
    {
      "pool_name": "S端dbad",
      "facility_type": "pool",
      "occupancy_level": "54 % frei",
      "occupancy_percent": 54.0,
      "is_open": true,
      "timestamp": "2026-02-15T17:24:16.264513+01:00",
      "hour": 17,
      "day_of_week": 6,
      "day_name": "Sunday",
      "is_weekend": true,
      "raw_occupancy": "145/314 persons"
    },
    {
      "pool_name": "Westbad",
      "facility_type": "pool",
      "occupancy_level": "20 % frei",
      "occupancy_percent": 20.0,
      "is_open": true,
      "timestamp": "2026-02-15T17:24:16.264513+01:00",
      "hour": 17,
      "day_of_week": 6,
      "day_name": "Sunday",
      "is_weekend": true,
      "raw_occupancy": "697/872 persons"
    }
  ],
  "saunas": [
    {
      "pool_name": "Cosimawellenbad",
      "facility_type": "sauna",
      "occupancy_level": "74 % frei",
      "occupancy_percent": 74.0,
      "is_open": true,
      "timestamp": "2026-02-15T17:24:16.264513+01:00",
      "hour": 17,
      "day_of_week": 6,
      "day_name": "Sunday",
      "is_weekend": true,
      "raw_occupancy": "44/170 persons"
    },
    {
      "pool_name": "Dantebad",
      "facility_type": "sauna",
      "occupancy_level": "38 % frei",
      "occupancy_percent": 38.0,
      "is_open": true,
      "timestamp": "2026-02-15T17:24:16.264513+01:00",
      "hour": 17,
      "day_of_week": 6,
      "day_name": "Sunday",
      "is_weekend": true,
      "raw_occupancy": "93/150 persons"
    },
    {
      "pool_name": "Michaelibad",
      "facility_type": "sauna",
      "occupancy_level": "59 % frei",
      "occupancy_percent": 59.0,
      "is_open": true,
      "timestamp": "2026-02-15T17:24:16.264513+01:00",
      "hour": 17,
      "day_of_week": 6,
      "day_name": "Sunday",
      "is_weekend": true,
      "raw_occupancy": "62/150 persons"
    },
    {
      "pool_name": "M端ller'sches Volksbad",
      "facility_type": "sauna",
      "occupancy_level": "0 % frei",
      "occupancy_percent": 0.0,
      "is_open": true,
      "timestamp": "2026-02-15T17:24:16.264513+01:00",
      "hour": 17,
      "day_of_week": 6,
      "day_name": "Sunday",
      "is_weekend": true,
      "raw_occupancy": "70/70 persons"
    },
    {
      "pool_name": "Nordbad",
      "facility_type": "sauna",
      "occupancy_level": "60 % frei",
      "occupancy_percent": 60.0,
      "is_open": true,
      "timestamp": "2026-02-15T17:24:16.264513+01:00",
      "hour": 17,
      "day_of_week": 6,
      "day_name": "Sunday",
      "is_weekend": true,
      "raw_occupancy": "58/146 persons"
    },
    {
      "pool_name": "S端dbad",
      "facility_type": "sauna",
      "occupancy_level": "54 % frei",
      "occupancy_percent": 54.0,
      "is_open": true,
      "timestamp": "2026-02-15T17:24:16.264513+01:00",
      "hour": 17,
      "day_of_week": 6,
      "day_name": "Sunday",
      "is_weekend": true,
      "raw_occupancy": "46/100 persons"
    },
    {
      "pool_name": "Westbad",
      "facility_type": "sauna",
      "occupancy_level": "63 % frei",
      "occupancy_percent": 63.0,
      "is_open": true,
      "timestamp": "2026-02-15T17:24:16.264513+01:00",
      "hour": 17,
      "day_of_week": 6,
      "day_name": "Sunday",
      "is_weekend": true,
      "raw_occupancy": "22/60 persons"
    }
  ],
  "summary": {
    "avg_pool_occupancy": 49.888888888888886,
    "busiest_pool": "Bad Giesing-Harlaching",
    "quietest_pool": "Michaelibad"
  }
}