{
  "scrape_timestamp": "2026-01-18T09:04:41.694598+01:00",
  "scrape_metadata": {
    "total_facilities": 13,
    "pools_count": 7,
    "saunas_count": 6,
    "unknown_count": 0,
    "scrape_duration_ms": 3579.814910888672,
    "hour": 9,
    "day_of_week": 6,
    "is_weekend": true,
    "duration_ms": 3579.814910888672,
    "method": "api"
  },
  "pools": [
    {
      "pool_name": "Bad Giesing-Harlaching",
      "facility_type": "pool",
      "occupancy_level": "79 % frei",
      "occupancy_percent": 79.0,
      "is_open": true,
      "timestamp": "2026-01-18T09:04:38.115104+01:00",
      "hour": 9,
      "day_of_week": 6,
      "day_name": "Sunday",
      "is_weekend": true,
      "raw_occupancy": "66/311 persons"
    },
    {
      "pool_name": "Cosimawellenbad",
      "facility_type": "pool",
      "occupancy_level": "88 % frei",
      "occupancy_percent": 88.0,
      "is_open": true,
      "timestamp": "2026-01-18T09:04:38.115104+01:00",
      "hour": 9,
      "day_of_week": 6,
      "day_name": "Sunday",
      "is_weekend": true,
      "raw_occupancy": "61/530 persons"
    },
    {
      "pool_name": "Michaelibad",
      "facility_type": "pool",
      "occupancy_level": "79 % frei",
      "occupancy_percent": 79.0,
      "is_open": true,
      "timestamp": "2026-01-18T09:04:38.115104+01:00",
      "hour": 9,
      "day_of_week": 6,
      "day_name": "Sunday",
      "is_weekend": true,
      "raw_occupancy": "121/570 persons"
    },
    {
      "pool_name": "Nordbad",
      "facility_type": "pool",
      "occupancy_level": "82 % frei",
      "occupancy_percent": 82.0,
      "is_open": true,
      "timestamp": "2026-01-18T09:04:38.115104+01:00",
      "hour": 9,
      "day_of_week": 6,
      "day_name": "Sunday",
      "is_weekend": true,
      "raw_occupancy": "31/177 persons"
    },
    {
      "pool_name": "Südbad",
      "facility_type": "pool",
      "occupancy_level": "76 % frei",
      "occupancy_percent": 76.0,
      "is_open": true,
      "timestamp": "2026-01-18T09:04:38.115104+01:00",
      "hour": 9,
      "day_of_week": 6,
      "day_name": "Sunday",
      "is_weekend": true,
      "raw_occupancy": "103/432 persons"
    },
    {
      "pool_name": "Westbad",
      "facility_type": "pool",
      "occupancy_level": "79 % frei",
      "occupancy_percent": 79.0,
      "is_open": true,
      "timestamp": "2026-01-18T09:04:38.115104+01:00",
      "hour": 9,
      "day_of_week": 6,
      "day_name": "Sunday",
      "is_weekend": true,
      "raw_occupancy": "67/314 persons"
    },
    {
      "pool_name": "Müller'sches Volksbad",
      "facility_type": "pool",
      "occupancy_level": "91 % frei",
      "occupancy_percent": 91.0,
      "is_open": true,
      "timestamp": "2026-01-18T09:04:38.115104+01:00",
      "hour": 9,
      "day_of_week": 6,
      "day_name": "Sunday",
      "is_weekend": true,
      "raw_occupancy": "82/872 persons"
    }
  ],
  "saunas": [
    {
      "pool_name": "Cosimawellenbad Sauna",
      "facility_type": "sauna",
      "occupancy_level": "99 % frei",
      "occupancy_percent": 99.0,
      "is_open": true,
      "timestamp": "2026-01-18T09:04:38.115104+01:00",
      "hour": 9,
      "day_of_week": 6,
      "day_name": "Sunday",
      "is_weekend": true,
      "raw_occupancy": "2/170 persons"
    },
    {
      "pool_name": "Dantebad Sauna",
      "facility_type": "sauna",
      "occupancy_level": "89 % frei",
      "occupancy_percent": 89.0,
      "is_open": true,
      "timestamp": "2026-01-18T09:04:38.115104+01:00",
      "hour": 9,
      "day_of_week": 6,
      "day_name": "Sunday",
      "is_weekend": true,
      "raw_occupancy": "16/150 persons"
    },
    {
      "pool_name": "Michaelibad Sauna",
      "facility_type": "sauna",
      "occupancy_level": "89 % frei",
      "occupancy_percent": 89.0,
      "is_open": true,
      "timestamp": "2026-01-18T09:04:38.115104+01:00",
      "hour": 9,
      "day_of_week": 6,
      "day_name": "Sunday",
      "is_weekend": true,
      "raw_occupancy": "17/150 persons"
    },
    {
      "pool_name": "Nordbad Sauna",
      "facility_type": "sauna",
      "occupancy_level": "94 % frei",
      "occupancy_percent": 94.0,
      "is_open": true,
      "timestamp": "2026-01-18T09:04:38.115104+01:00",
      "hour": 9,
      "day_of_week": 6,
      "day_name": "Sunday",
      "is_weekend": true,
      "raw_occupancy": "9/146 persons"
    },
    {
      "pool_name": "Südbad Sauna",
      "facility_type": "sauna",
      "occupancy_level": "99 % frei",
      "occupancy_percent": 99.0,
      "is_open": true,
      "timestamp": "2026-01-18T09:04:38.115104+01:00",
      "hour": 9,
      "day_of_week": 6,
      "day_name": "Sunday",
      "is_weekend": true,
      "raw_occupancy": "1/100 persons"
    },
    {
      "pool_name": "Westbad Sauna",
      "facility_type": "sauna",
      "occupancy_level": "87 % frei",
      "occupancy_percent": 87.0,
      "is_open": true,
      "timestamp": "2026-01-18T09:04:38.115104+01:00",
      "hour": 9,
      "day_of_week": 6,
      "day_name": "Sunday",
      "is_weekend": true,
      "raw_occupancy": "8/60 persons"
    }
  ],
  "unknown_facilities": [],
  "summary": {
    "avg_pool_occupancy": 82.0,
    "avg_sauna_occupancy": 92.83333333333333,
    "busiest_pool": "Müller'sches Volksbad",
    "quietest_pool": "Südbad"
  }
}